[{"Color":"Black","Start":{"IsEmpty":false,"X":187.0,"Y":204.0},"End":{"IsEmpty":false,"X":189.0,"Y":196.0}},
{"Color":"Black","Start":{"IsEmpty":false,"X":171.0,"Y":204.0},"End":{"IsEmpty":false,"X":187.0,"Y":204.0}},
{"Color":"Black","Start":{"IsEmpty":false,"X":189.0,"Y":196.0},"End":{"IsEmpty":false,"X":173.0,"Y":194.0}},
{"Color":"Black","Start":{"IsEmpty":false,"X":110.0,"Y":404.0},"End":{"IsEmpty":false,"X":187.0,"Y":204.0}},
{"Color":"Black","Start":{"IsEmpty":false,"X":78.0,"Y":444.0},"End":{"IsEmpty":false,"X":110.0,"Y":404.0}},
{"Color":"Black","Start":{"IsEmpty":false,"X":104.0,"Y":411.0},"End":{"IsEmpty":false,"X":72.0,"Y":452.0}},
{"Color":"Black","Start":{"IsEmpty":false,"X":104.0,"Y":411.0},"End":{"IsEmpty":false,"X":110.0,"Y":404.0}},
{"Color":"Black","Start":{"IsEmpty":false,"X":-37.0,"Y":175.0},"End":{"IsEmpty":false,"X":14.0,"Y":180.0}},
{"Color":"Black","Start":{"IsEmpty":false,"X":28.0,"Y":190.0},"End":{"IsEmpty":false,"X":23.0,"Y":183.0}},
{"Color":"Black","Start":{"IsEmpty":false,"X":-19.0,"Y":186.0},"End":{"IsEmpty":false,"X":28.0,"Y":190.0}},
{"Color":"Black","Start":{"IsEmpty":false,"X":23.0,"Y":183.0},"End":{"IsEmpty":false,"X":-26.0,"Y":178.0}},
{"Color":"Black","Start":{"IsEmpty":false,"X":23.0,"Y":183.0},"End":{"IsEmpty":false,"X":14.0,"Y":180.0}},
{"Color":"Black","Start":{"IsEmpty":false,"X":83.0,"Y":327.0},"End":{"IsEmpty":false,"X":28.0,"Y":190.0}},
{"Color":"Black","Start":{"IsEmpty":false,"X":161.0,"Y":177.0},"End":{"IsEmpty":false,"X":179.0,"Y":181.0}},
{"Color":"Black","Start":{"IsEmpty":false,"X":184.0,"Y":185.0},"End":{"IsEmpty":false,"X":179.0,"Y":181.0}},
{"Color":"Black","Start":{"IsEmpty":false,"X":167.0,"Y":181.0},"End":{"IsEmpty":false,"X":184.0,"Y":185.0}},
{"Color":"Black","Start":{"IsEmpty":false,"X":187.0,"Y":190.0},"End":{"IsEmpty":false,"X":184.0,"Y":185.0}},
{"Color":"Black","Start":{"IsEmpty":false,"X":172.0,"Y":187.0},"End":{"IsEmpty":false,"X":187.0,"Y":190.0}},
{"Color":"Black","Start":{"IsEmpty":false,"X":189.0,"Y":196.0},"End":{"IsEmpty":false,"X":187.0,"Y":190.0}},
{"Color":"Black","Start":{"IsEmpty":false,"X":382.0,"Y":337.0},"End":{"IsEmpty":false,"X":368.0,"Y":321.0}},
{"Color":"Black","Start":{"IsEmpty":false,"X":369.0,"Y":327.0},"End":{"IsEmpty":false,"X":377.0,"Y":336.0}},
{"Color":"Black","Start":{"IsEmpty":false,"X":432.0,"Y":315.0},"End":{"IsEmpty":false,"X":368.0,"Y":315.0}},
{"Color":"Black","Start":{"IsEmpty":false,"X":466.0,"Y":337.0},"End":{"IsEmpty":false,"X":432.0,"Y":315.0}},
{"Color":"Black","Start":{"IsEmpty":false,"X":438.0,"Y":317.0},"End":{"IsEmpty":false,"X":473.0,"Y":339.0}},
{"Color":"Black","Start":{"IsEmpty":false,"X":438.0,"Y":317.0},"End":{"IsEmpty":false,"X":432.0,"Y":315.0}},
{"Color":"Black","Start":{"IsEmpty":false,"X":487.0,"Y":347.0},"End":{"IsEmpty":false,"X":479.0,"Y":346.0}},
{"Color":"Black","Start":{"IsEmpty":false,"X":532.0,"Y":375.0},"End":{"IsEmpty":false,"X":487.0,"Y":347.0}},
{"Color":"Black","Start":{"IsEmpty":false,"X":484.0,"Y":353.0},"End":{"IsEmpty":false,"X":516.0,"Y":374.0}},
{"Color":"Black","Start":{"IsEmpty":false,"X":493.0,"Y":348.0},"End":{"IsEmpty":false,"X":539.0,"Y":377.0}},
{"Color":"Black","Start":{"IsEmpty":false,"X":493.0,"Y":348.0},"End":{"IsEmpty":false,"X":487.0,"Y":347.0}},
{"Color":"Black","Start":{"IsEmpty":false,"X":604.0,"Y":459.0},"End":{"IsEmpty":false,"X":576.0,"Y":438.0}},
{"Color":"Black","Start":{"IsEmpty":false,"X":581.0,"Y":447.0},"End":{"IsEmpty":false,"X":599.0,"Y":461.0}},
{"Color":"Black","Start":{"IsEmpty":false,"X":585.0,"Y":454.0},"End":{"IsEmpty":false,"X":593.0,"Y":460.0}},
{"Color":"Black","Start":{"IsEmpty":false,"X":616.0,"Y":452.0},"End":{"IsEmpty":false,"X":563.0,"Y":414.0}},
{"Color":"Black","Start":{"IsEmpty":false,"X":562.0,"Y":395.0},"End":{"IsEmpty":false,"X":563.0,"Y":399.0}},
{"Color":"Black","Start":{"IsEmpty":false,"X":622.0,"Y":433.0},"End":{"IsEmpty":false,"X":562.0,"Y":395.0}},
{"Color":"Black","Start":{"IsEmpty":false,"X":563.0,"Y":399.0},"End":{"IsEmpty":false,"X":623.0,"Y":438.0}},
{"Color":"Black","Start":{"IsEmpty":false,"X":563.0,"Y":399.0},"End":{"IsEmpty":false,"X":563.0,"Y":404.0}},
{"Color":"Black","Start":{"IsEmpty":false,"X":563.0,"Y":404.0},"End":{"IsEmpty":false,"X":623.0,"Y":444.0}},
{"Color":"Black","Start":{"IsEmpty":false,"X":563.0,"Y":404.0},"End":{"IsEmpty":false,"X":561.0,"Y":408.0}},
{"Color":"Black","Start":{"IsEmpty":false,"X":561.0,"Y":408.0},"End":{"IsEmpty":false,"X":620.0,"Y":448.0}},
{"Color":"Black","Start":{"IsEmpty":false,"X":561.0,"Y":408.0},"End":{"IsEmpty":false,"X":559.0,"Y":409.0}},
{"Color":"Black","Start":{"IsEmpty":false,"X":528.0,"Y":335.0},"End":{"IsEmpty":false,"X":562.0,"Y":395.0}},
{"Color":"Black","Start":{"IsEmpty":false,"X":581.0,"Y":361.0},"End":{"IsEmpty":false,"X":528.0,"Y":335.0}},
{"Color":"Black","Start":{"IsEmpty":false,"X":528.0,"Y":323.0},"End":{"IsEmpty":false,"X":526.0,"Y":329.0}},
{"Color":"Black","Start":{"IsEmpty":false,"X":582.0,"Y":347.0},"End":{"IsEmpty":false,"X":528.0,"Y":323.0}},
{"Color":"Black","Start":{"IsEmpty":false,"X":526.0,"Y":329.0},"End":{"IsEmpty":false,"X":579.0,"Y":354.0}},
{"Color":"Black","Start":{"IsEmpty":false,"X":526.0,"Y":329.0},"End":{"IsEmpty":false,"X":528.0,"Y":335.0}},
{"Color":"Black","Start":{"IsEmpty":false,"X":529.0,"Y":271.0},"End":{"IsEmpty":false,"X":534.0,"Y":284.0}},
{"Color":"Black","Start":{"IsEmpty":false,"X":583.0,"Y":285.0},"End":{"IsEmpty":false,"X":529.0,"Y":271.0}},
{"Color":"Black","Start":{"IsEmpty":false,"X":534.0,"Y":284.0},"End":{"IsEmpty":false,"X":589.0,"Y":300.0}},
{"Color":"Black","Start":{"IsEmpty":false,"X":534.0,"Y":284.0},"End":{"IsEmpty":false,"X":536.0,"Y":297.0}},
{"Color":"Black","Start":{"IsEmpty":false,"X":536.0,"Y":297.0},"End":{"IsEmpty":false,"X":591.0,"Y":316.0}},
{"Color":"Black","Start":{"IsEmpty":false,"X":536.0,"Y":297.0},"End":{"IsEmpty":false,"X":534.0,"Y":311.0}},
{"Color":"Black","Start":{"IsEmpty":false,"X":534.0,"Y":311.0},"End":{"IsEmpty":false,"X":588.0,"Y":332.0}},
{"Color":"Black","Start":{"IsEmpty":false,"X":534.0,"Y":311.0},"End":{"IsEmpty":false,"X":528.0,"Y":323.0}},
{"Color":"Black","Start":{"IsEmpty":false,"X":529.0,"Y":259.0},"End":{"IsEmpty":false,"X":527.0,"Y":266.0}},
{"Color":"Black","Start":{"IsEmpty":false,"X":583.0,"Y":271.0},"End":{"IsEmpty":false,"X":529.0,"Y":259.0}},
{"Color":"Black","Start":{"IsEmpty":false,"X":527.0,"Y":266.0},"End":{"IsEmpty":false,"X":581.0,"Y":278.0}},
{"Color":"Black","Start":{"IsEmpty":false,"X":527.0,"Y":266.0},"End":{"IsEmpty":false,"X":529.0,"Y":271.0}},
{"Color":"Black","Start":{"IsEmpty":false,"X":531.0,"Y":257.0},"End":{"IsEmpty":false,"X":529.0,"Y":259.0}},
{"Color":"Black","Start":{"IsEmpty":false,"X":626.0,"Y":198.0},"End":{"IsEmpty":false,"X":577.0,"Y":199.0}},
{"Color":"Black","Start":{"IsEmpty":false,"X":621.0,"Y":178.0},"End":{"IsEmpty":false,"X":587.0,"Y":181.0}},
{"Color":"Black","Start":{"IsEmpty":false,"X":585.0,"Y":185.0},"End":{"IsEmpty":false,"X":626.0,"Y":182.0}},
{"Color":"Black","Start":{"IsEmpty":false,"X":582.0,"Y":189.0},"End":{"IsEmpty":false,"X":628.0,"Y":187.0}},
{"Color":"Black","Start":{"IsEmpty":false,"X":579.0,"Y":194.0},"End":{"IsEmpty":false,"X":628.0,"Y":192.0}},
{"Color":"Black","Start":{"IsEmpty":false,"X":609.0,"Y":171.0},"End":{"IsEmpty":false,"X":594.0,"Y":173.0}},
{"Color":"Black","Start":{"IsEmpty":false,"X":538.0,"Y":134.0},"End":{"IsEmpty":false,"X":582.0,"Y":123.0}},
{"Color":"Black","Start":{"IsEmpty":false,"X":536.0,"Y":137.0},"End":{"IsEmpty":false,"X":578.0,"Y":126.0}},
{"Color":"Black","Start":{"IsEmpty":false,"X":323.0,"Y":333.0},"End":{"IsEmpty":false,"X":326.0,"Y":340.0}},
{"Color":"Black","Start":{"IsEmpty":false,"X":335.0,"Y":359.0},"End":{"IsEmpty":false,"X":323.0,"Y":333.0}},
{"Color":"Black","Start":{"IsEmpty":false,"X":326.0,"Y":340.0},"End":{"IsEmpty":false,"X":338.0,"Y":368.0}},
{"Color":"Black","Start":{"IsEmpty":false,"X":324.0,"Y":261.0},"End":{"IsEmpty":false,"X":323.0,"Y":333.0}},
{"Color":"Black","Start":{"IsEmpty":false,"X":336.0,"Y":273.0},"End":{"IsEmpty":false,"X":324.0,"Y":261.0}},
{"Color":"Black","Start":{"IsEmpty":false,"X":332.0,"Y":250.0},"End":{"IsEmpty":false,"X":326.0,"Y":254.0}},
{"Color":"Black","Start":{"IsEmpty":false,"X":346.0,"Y":259.0},"End":{"IsEmpty":false,"X":332.0,"Y":250.0}},
{"Color":"Black","Start":{"IsEmpty":false,"X":326.0,"Y":254.0},"End":{"IsEmpty":false,"X":338.0,"Y":264.0}},
{"Color":"Black","Start":{"IsEmpty":false,"X":326.0,"Y":254.0},"End":{"IsEmpty":false,"X":324.0,"Y":261.0}},
{"Color":"Black","Start":{"IsEmpty":false,"X":511.0,"Y":151.0},"End":{"IsEmpty":false,"X":481.0,"Y":175.0}},
{"Color":"Black","Start":{"IsEmpty":false,"X":481.0,"Y":175.0},"End":{"IsEmpty":false,"X":526.0,"Y":169.0}},
{"Color":"Black","Start":{"IsEmpty":false,"X":481.0,"Y":175.0},"End":{"IsEmpty":false,"X":434.0,"Y":206.0}},
{"Color":"Black","Start":{"IsEmpty":false,"X":434.0,"Y":206.0},"End":{"IsEmpty":false,"X":469.0,"Y":206.0}},
{"Color":"Black","Start":{"IsEmpty":false,"X":434.0,"Y":206.0},"End":{"IsEmpty":false,"X":384.0,"Y":231.0}},
{"Color":"Black","Start":{"IsEmpty":false,"X":384.0,"Y":231.0},"End":{"IsEmpty":false,"X":409.0,"Y":236.0}},
{"Color":"Black","Start":{"IsEmpty":false,"X":384.0,"Y":231.0},"End":{"IsEmpty":false,"X":332.0,"Y":250.0}},
{"Color":"Black","Start":{"IsEmpty":false,"X":731.0,"Y":463.0},"End":{"IsEmpty":false,"X":667.0,"Y":428.0}},
{"Color":"Black","Start":{"IsEmpty":false,"X":669.0,"Y":436.0},"End":{"IsEmpty":false,"X":729.0,"Y":470.0}},
{"Color":"Black","Start":{"IsEmpty":false,"X":670.0,"Y":443.0},"End":{"IsEmpty":false,"X":725.0,"Y":476.0}},
{"Color":"Black","Start":{"IsEmpty":false,"X":670.0,"Y":449.0},"End":{"IsEmpty":false,"X":720.0,"Y":479.0}},
{"Color":"Black","Start":{"IsEmpty":false,"X":669.0,"Y":454.0},"End":{"IsEmpty":false,"X":713.0,"Y":481.0}},
{"Color":"Black","Start":{"IsEmpty":false,"X":738.0,"Y":166.0},"End":{"IsEmpty":false,"X":673.0,"Y":172.0}},
{"Color":"Black","Start":{"IsEmpty":false,"X":721.0,"Y":148.0},"End":{"IsEmpty":false,"X":651.0,"Y":157.0}},
{"Color":"Black","Start":{"IsEmpty":false,"X":654.0,"Y":159.0},"End":{"IsEmpty":false,"X":728.0,"Y":150.0}},
{"Color":"Black","Start":{"IsEmpty":false,"X":659.0,"Y":162.0},"End":{"IsEmpty":false,"X":733.0,"Y":154.0}},
{"Color":"Black","Start":{"IsEmpty":false,"X":667.0,"Y":166.0},"End":{"IsEmpty":false,"X":737.0,"Y":159.0}},
{"Color":"Black","Start":{"IsEmpty":false,"X":676.0,"Y":148.0},"End":{"IsEmpty":false,"X":644.0,"Y":153.0}},
{"Color":"Black","Start":{"IsEmpty":false,"X":630.0,"Y":122.0},"End":{"IsEmpty":false,"X":602.0,"Y":128.0}},
{"Color":"Black","Start":{"IsEmpty":false,"X":623.0,"Y":506.0},"End":{"IsEmpty":false,"X":607.0,"Y":493.0}},
{"Color":"Black","Start":{"IsEmpty":false,"X":668.0,"Y":481.0},"End":{"IsEmpty":false,"X":651.0,"Y":469.0}},
{"Color":"Black","Start":{"IsEmpty":false,"X":500.0,"Y":456.0},"End":{"IsEmpty":false,"X":548.0,"Y":506.0}},
{"Color":"Black","Start":{"IsEmpty":false,"X":521.0,"Y":148.0},"End":{"IsEmpty":false,"X":478.0,"Y":158.0}},
{"Color":"Black","Start":{"IsEmpty":false,"X":-9.0,"Y":158.0},"End":{"IsEmpty":false,"X":478.0,"Y":158.0}},
{"Color":"Black","Start":{"IsEmpty":false,"X":-65.0,"Y":148.0},"End":{"IsEmpty":false,"X":-9.0,"Y":158.0}},
{"Color":"Black","Start":{"IsEmpty":false,"X":-24.0,"Y":173.0},"End":{"IsEmpty":false,"X":-23.0,"Y":167.0}},
{"Color":"Black","Start":{"IsEmpty":false,"X":-83.0,"Y":166.0},"End":{"IsEmpty":false,"X":-24.0,"Y":173.0}},
{"Color":"Black","Start":{"IsEmpty":false,"X":-23.0,"Y":167.0},"End":{"IsEmpty":false,"X":-82.0,"Y":159.0}},
{"Color":"Black","Start":{"IsEmpty":false,"X":-23.0,"Y":167.0},"End":{"IsEmpty":false,"X":-19.0,"Y":162.0}},
{"Color":"Black","Start":{"IsEmpty":false,"X":-19.0,"Y":162.0},"End":{"IsEmpty":false,"X":-78.0,"Y":153.0}},
{"Color":"Black","Start":{"IsEmpty":false,"X":-19.0,"Y":162.0},"End":{"IsEmpty":false,"X":-15.0,"Y":159.0}},
{"Color":"Black","Start":{"IsEmpty":false,"X":-15.0,"Y":159.0},"End":{"IsEmpty":false,"X":-72.0,"Y":150.0}},
{"Color":"Black","Start":{"IsEmpty":false,"X":-15.0,"Y":159.0},"End":{"IsEmpty":false,"X":-9.0,"Y":158.0}},
{"Color":"Black","Start":{"IsEmpty":false,"X":-20.0,"Y":420.0},"End":{"IsEmpty":false,"X":-22.0,"Y":279.0}},
{"Color":"Black","Start":{"IsEmpty":false,"X":-24.0,"Y":176.0},"End":{"IsEmpty":false,"X":-24.0,"Y":173.0}},
{"Color":"Black","Start":{"IsEmpty":false,"X":-77.0,"Y":464.0},"End":{"IsEmpty":false,"X":-20.0,"Y":420.0}},
{"Color":"Black","Start":{"IsEmpty":false,"X":-5.0,"Y":435.0},"End":{"IsEmpty":false,"X":-11.0,"Y":434.0}},
{"Color":"Black","Start":{"IsEmpty":false,"X":-59.0,"Y":481.0},"End":{"IsEmpty":false,"X":-5.0,"Y":435.0}},
{"Color":"Black","Start":{"IsEmpty":false,"X":-11.0,"Y":434.0},"End":{"IsEmpty":false,"X":-66.0,"Y":480.0}},
{"Color":"Black","Start":{"IsEmpty":false,"X":-11.0,"Y":434.0},"End":{"IsEmpty":false,"X":-15.0,"Y":431.0}},
{"Color":"Black","Start":{"IsEmpty":false,"X":-15.0,"Y":431.0},"End":{"IsEmpty":false,"X":-72.0,"Y":476.0}},
{"Color":"Black","Start":{"IsEmpty":false,"X":-15.0,"Y":431.0},"End":{"IsEmpty":false,"X":-18.0,"Y":426.0}},
{"Color":"Black","Start":{"IsEmpty":false,"X":-18.0,"Y":426.0},"End":{"IsEmpty":false,"X":-76.0,"Y":471.0}},
{"Color":"Black","Start":{"IsEmpty":false,"X":-18.0,"Y":426.0},"End":{"IsEmpty":false,"X":-20.0,"Y":420.0}},
{"Color":"Black","Start":{"IsEmpty":false,"X":474.0,"Y":435.0},"End":{"IsEmpty":false,"X":273.0,"Y":435.0}},
{"Color":"Black","Start":{"IsEmpty":false,"X":237.0,"Y":435.0},"End":{"IsEmpty":false,"X":85.0,"Y":435.0}},
{"Color":"Black","Start":{"IsEmpty":false,"X":41.0,"Y":435.0},"End":{"IsEmpty":false,"X":-5.0,"Y":435.0}},
{"Color":"Black","Start":{"IsEmpty":false,"X":517.0,"Y":481.0},"End":{"IsEmpty":false,"X":474.0,"Y":435.0}},
{"Color":"Black","Start":{"IsEmpty":false,"X":500.0,"Y":456.0},"End":{"IsEmpty":false,"X":474.0,"Y":435.0}},
{"Color":"Purple","Path":[]},
{"Color":"Purple","Path":[{"Item1":{"IsEmpty":false,"X":51.4894371,"Y":452.8385},"Item2":{"IsEmpty":false,"X":44.78292,"Y":444.172852}}]},
{"Color":"Purple","Path":[{"Item1":{"IsEmpty":false,"X":-26.5384445,"Y":178.395416},"Item2":{"IsEmpty":false,"X":-19.5726128,"Y":186.792038}}]},
{"Color":"Purple","Path":[{"Item1":{"IsEmpty":false,"X":143.6632,"Y":178.408508},"Item2":{"IsEmpty":false,"X":154.554916,"Y":175.611481}}]},
{"Color":"Purple","Path":[{"Item1":{"IsEmpty":false,"X":173.454651,"Y":194.43161},"Item2":{"IsEmpty":false,"X":171.377151,"Y":204.0043}},
{"Item1":{"IsEmpty":false,"X":171.377151,"Y":204.0043},"Item2":{"IsEmpty":false,"X":78.71682,"Y":444.150177}},
{"Item1":{"IsEmpty":false,"X":78.71682,"Y":444.150177},"Item2":{"IsEmpty":false,"X":72.20647,"Y":452.824158}},
{"Item1":{"IsEmpty":false,"X":72.20647,"Y":452.824158},"Item2":{"IsEmpty":false,"X":61.8807564,"Y":455.719421}},
{"Item1":{"IsEmpty":false,"X":61.8807564,"Y":455.719421},"Item2":{"IsEmpty":false,"X":51.4894371,"Y":452.8385}},
{"Item1":{"IsEmpty":false,"X":44.78292,"Y":444.172852},"Item2":{"IsEmpty":false,"X":-53.3522835,"Y":204.003143}},
{"Item1":{"IsEmpty":false,"X":-53.3522835,"Y":204.003143},"Item2":{"IsEmpty":false,"X":-55.648098,"Y":194.424271}},
{"Item1":{"IsEmpty":false,"X":-55.648098,"Y":194.424271},"Item2":{"IsEmpty":false,"X":-54.3543777,"Y":187.145645}},
{"Item1":{"IsEmpty":false,"X":-54.3543777,"Y":187.145645},"Item2":{"IsEmpty":false,"X":-50.55408,"Y":181.104721}},
{"Item1":{"IsEmpty":false,"X":-50.55408,"Y":181.104721},"Item2":{"IsEmpty":false,"X":-44.58563,"Y":177.016876}},
{"Item1":{"IsEmpty":false,"X":-44.58563,"Y":177.016876},"Item2":{"IsEmpty":false,"X":-37.150032,"Y":175.595215}},
{"Item1":{"IsEmpty":false,"X":-37.150032,"Y":175.595215},"Item2":{"IsEmpty":false,"X":-26.5384445,"Y":178.395416}},
{"Item1":{"IsEmpty":false,"X":-19.5726128,"Y":186.792038},"Item2":{"IsEmpty":false,"X":61.10164,"Y":386.4923}},
{"Item1":{"IsEmpty":false,"X":61.10164,"Y":386.4923},"Item2":{"IsEmpty":false,"X":137.246475,"Y":186.800415}},
{"Item1":{"IsEmpty":false,"X":137.246475,"Y":186.800415},"Item2":{"IsEmpty":false,"X":143.6632,"Y":178.408508}},
{"Item1":{"IsEmpty":false,"X":154.554916,"Y":175.611481},"Item2":{"IsEmpty":false,"X":161.83728,"Y":177.033554}},
{"Item1":{"IsEmpty":false,"X":161.83728,"Y":177.033554},"Item2":{"IsEmpty":false,"X":167.889465,"Y":181.119873}},
{"Item1":{"IsEmpty":false,"X":167.889465,"Y":181.119873},"Item2":{"IsEmpty":false,"X":172.000046,"Y":187.1575}},
{"Item1":{"IsEmpty":false,"X":172.000046,"Y":187.1575},"Item2":{"IsEmpty":false,"X":173.454651,"Y":194.43161}}]},
{"Color":"Purple","Path":[{"Item1":{"IsEmpty":false,"X":377.20694,"Y":336.517059},"Item2":{"IsEmpty":false,"X":382.672638,"Y":337.6137}},
{"Item1":{"IsEmpty":false,"X":372.753754,"Y":333.523865},"Item2":{"IsEmpty":false,"X":377.20694,"Y":336.517059}},
{"Item1":{"IsEmpty":false,"X":369.765,"Y":329.080017},"Item2":{"IsEmpty":false,"X":372.753754,"Y":333.523865}}]},
{"Color":"Purple","Path":[{"Item1":{"IsEmpty":false,"X":473.706665,"Y":339.547028},"Item2":{"IsEmpty":false,"X":478.808533,"Y":344.8902}}]},
{"Color":"Purple","Path":[{"Item1":{"IsEmpty":false,"X":516.0869,"Y":374.037445},"Item2":{"IsEmpty":false,"X":532.4665,"Y":375.8535}},
{"Item1":{"IsEmpty":false,"X":501.1529,"Y":367.969147},"Item2":{"IsEmpty":false,"X":516.0869,"Y":374.037445}},
{"Item1":{"IsEmpty":false,"X":488.459747,"Y":358.102631},"Item2":{"IsEmpty":false,"X":501.1529,"Y":367.969147}}]},
{"Color":"Purple","Path":[{"Item1":{"IsEmpty":false,"X":539.6653,"Y":377.613831},"Item2":{"IsEmpty":false,"X":544.882568,"Y":382.793732}}]},
{"Color":"Purple","Path":[{"Item1":{"IsEmpty":false,"X":599.1036,"Y":461.052338},"Item2":{"IsEmpty":false,"X":604.385254,"Y":459.3046}},
{"Item1":{"IsEmpty":false,"X":593.776245,"Y":460.689545},"Item2":{"IsEmpty":false,"X":599.1036,"Y":461.052338}},
{"Item1":{"IsEmpty":false,"X":589.0114,"Y":458.377045},"Item2":{"IsEmpty":false,"X":593.776245,"Y":460.689545}}]},
{"Color":"Purple","Path":[{"Item1":{"IsEmpty":false,"X":623.7392,"Y":438.751343},"Item2":{"IsEmpty":false,"X":622.073242,"Y":433.554932}},
{"Item1":{"IsEmpty":false,"X":623.2626,"Y":444.028748},"Item2":{"IsEmpty":false,"X":623.7392,"Y":438.751343}},
{"Item1":{"IsEmpty":false,"X":620.8241,"Y":448.782318},"Item2":{"IsEmpty":false,"X":623.2626,"Y":444.028748}}]},
{"Color":"Purple","Path":[{"Item1":{"IsEmpty":false,"X":579.886536,"Y":354.7574},"Item2":{"IsEmpty":false,"X":582.0835,"Y":347.6497}}]},
{"Color":"Purple","Path":[{"Item1":{"IsEmpty":false,"X":589.534851,"Y":300.526123},"Item2":{"IsEmpty":false,"X":583.1622,"Y":285.389038}},
{"Item1":{"IsEmpty":false,"X":591.4611,"Y":316.569641},"Item2":{"IsEmpty":false,"X":589.534851,"Y":300.526123}},
{"Item1":{"IsEmpty":false,"X":588.9678,"Y":332.587555},"Item2":{"IsEmpty":false,"X":591.4611,"Y":316.569641}}]},
{"Color":"Purple","Path":[{"Item1":{"IsEmpty":false,"X":581.2048,"Y":278.228455},"Item2":{"IsEmpty":false,"X":583.217468,"Y":271.005737}}]},
{"Color":"Purple","Path":[{"Item1":{"IsEmpty":false,"X":626.0337,"Y":182.393509},"Item2":{"IsEmpty":false,"X":621.888855,"Y":178.663666}},
{"Item1":{"IsEmpty":false,"X":628.3167,"Y":187.28476},"Item2":{"IsEmpty":false,"X":626.0337,"Y":182.393509}},
{"Item1":{"IsEmpty":false,"X":628.587769,"Y":192.710281},"Item2":{"IsEmpty":false,"X":628.3167,"Y":187.28476}}]},
{"Color":"Purple","Path":[{"Item1":{"IsEmpty":false,"X":595.851868,"Y":171.406784},"Item2":{"IsEmpty":false,"X":590.3062,"Y":176.758957}}]},
{"Color":"Purple","Path":[{"Item1":{"IsEmpty":false,"X":541.5053,"Y":255.145615},"Item2":{"IsEmpty":false,"X":534.206,"Y":256.9339}}]},
{"Color":"Purple","Path":[{"Item1":{"IsEmpty":false,"X":489.4747,"Y":274.911},"Item2":{"IsEmpty":false,"X":479.4693,"Y":288.2322}},
{"Item1":{"IsEmpty":false,"X":502.482361,"Y":264.9343},"Item2":{"IsEmpty":false,"X":489.4747,"Y":274.911}},
{"Item1":{"IsEmpty":false,"X":517.669,"Y":258.782532},"Item2":{"IsEmpty":false,"X":502.482361,"Y":264.9343}}]},
{"Color":"Purple","Path":[{"Item1":{"IsEmpty":false,"X":467.000641,"Y":295.586945},"Item2":{"IsEmpty":false,"X":382.9411,"Y":295.608124}},
{"Item1":{"IsEmpty":false,"X":382.9411,"Y":295.608124},"Item2":{"IsEmpty":false,"X":377.4494,"Y":296.711945}},
{"Item1":{"IsEmpty":false,"X":369.906525,"Y":304.177765},"Item2":{"IsEmpty":false,"X":368.768127,"Y":309.634033}},
{"Item1":{"IsEmpty":false,"X":372.951416,"Y":299.72},"Item2":{"IsEmpty":false,"X":369.906525,"Y":304.177765}},
{"Item1":{"IsEmpty":false,"X":377.4494,"Y":296.711945},"Item2":{"IsEmpty":false,"X":372.951416,"Y":299.72}},
{"Item1":{"IsEmpty":false,"X":368.768127,"Y":309.634033},"Item2":{"IsEmpty":false,"X":368.689423,"Y":323.636047}},
{"Item1":{"IsEmpty":false,"X":368.689423,"Y":323.636047},"Item2":{"IsEmpty":false,"X":369.765,"Y":329.080017}},
{"Item1":{"IsEmpty":false,"X":382.672638,"Y":337.6137},"Item2":{"IsEmpty":false,"X":466.5393,"Y":337.5827}},
{"Item1":{"IsEmpty":false,"X":466.5393,"Y":337.5827},"Item2":{"IsEmpty":false,"X":473.706665,"Y":339.547028}},
{"Item1":{"IsEmpty":false,"X":478.808533,"Y":344.8902},"Item2":{"IsEmpty":false,"X":488.459747,"Y":358.102631}},
{"Item1":{"IsEmpty":false,"X":532.4665,"Y":375.8535},"Item2":{"IsEmpty":false,"X":539.6653,"Y":377.613831}},
{"Item1":{"IsEmpty":false,"X":544.882568,"Y":382.793732},"Item2":{"IsEmpty":false,"X":585.419,"Y":454.275665}},
{"Item1":{"IsEmpty":false,"X":585.419,"Y":454.275665},"Item2":{"IsEmpty":false,"X":589.0114,"Y":458.377045}},
{"Item1":{"IsEmpty":false,"X":604.385254,"Y":459.3046},"Item2":{"IsEmpty":false,"X":616.598145,"Y":452.407227}},
{"Item1":{"IsEmpty":false,"X":616.598145,"Y":452.407227},"Item2":{"IsEmpty":false,"X":620.8241,"Y":448.782318}},
{"Item1":{"IsEmpty":false,"X":622.073242,"Y":433.554932},"Item2":{"IsEmpty":false,"X":581.643555,"Y":361.910828}},
{"Item1":{"IsEmpty":false,"X":581.643555,"Y":361.910828},"Item2":{"IsEmpty":false,"X":579.886536,"Y":354.7574}},
{"Item1":{"IsEmpty":false,"X":582.0835,"Y":347.6497},"Item2":{"IsEmpty":false,"X":588.9678,"Y":332.587555}},
{"Item1":{"IsEmpty":false,"X":583.1622,"Y":285.389038},"Item2":{"IsEmpty":false,"X":581.2048,"Y":278.228455}},
{"Item1":{"IsEmpty":false,"X":583.217468,"Y":271.005737},"Item2":{"IsEmpty":false,"X":626.6913,"Y":198.046555}},
{"Item1":{"IsEmpty":false,"X":626.6913,"Y":198.046555},"Item2":{"IsEmpty":false,"X":628.587769,"Y":192.710281}},
{"Item1":{"IsEmpty":false,"X":621.888855,"Y":178.663666},"Item2":{"IsEmpty":false,"X":609.754944,"Y":171.557648}},
{"Item1":{"IsEmpty":false,"X":609.754944,"Y":171.557648},"Item2":{"IsEmpty":false,"X":603.085754,"Y":169.656754}},
{"Item1":{"IsEmpty":false,"X":603.085754,"Y":169.656754},"Item2":{"IsEmpty":false,"X":595.851868,"Y":171.406784}},
{"Item1":{"IsEmpty":false,"X":590.3062,"Y":176.758957},"Item2":{"IsEmpty":false,"X":546.917969,"Y":249.891785}},
{"Item1":{"IsEmpty":false,"X":546.917969,"Y":249.891785},"Item2":{"IsEmpty":false,"X":541.5053,"Y":255.145615}},
{"Item1":{"IsEmpty":false,"X":534.206,"Y":256.9339},"Item2":{"IsEmpty":false,"X":517.669,"Y":258.782532}},
{"Item1":{"IsEmpty":false,"X":474.229431,"Y":293.608673},"Item2":{"IsEmpty":false,"X":467.000641,"Y":295.586945}},
{"Item1":{"IsEmpty":false,"X":479.4693,"Y":288.2322},"Item2":{"IsEmpty":false,"X":474.229431,"Y":293.608673}}]},
{"Color":"Purple","Path":[{"Item1":{"IsEmpty":false,"X":660.7281,"Y":382.505859},"Item2":{"IsEmpty":false,"X":670.7883,"Y":447.32135}},
{"Item1":{"IsEmpty":false,"X":658.308,"Y":316.5489},"Item2":{"IsEmpty":false,"X":660.7281,"Y":382.505859}},
{"Item1":{"IsEmpty":false,"X":663.597961,"Y":250.1111},"Item2":{"IsEmpty":false,"X":658.308,"Y":316.5489}}]},
{"Color":"Purple","Path":[{"Item1":{"IsEmpty":false,"X":669.8241,"Y":455.952545},"Item2":{"IsEmpty":false,"X":663.8524,"Y":462.422943}}]},
{"Color":"Purple","Path":[{"Item1":{"IsEmpty":false,"X":580.0528,"Y":506.5786},"Item2":{"IsEmpty":false,"X":572.183838,"Y":502.9478}}]},
{"Color":"Purple","Path":[{"Item1":{"IsEmpty":false,"X":408.1693,"Y":395.67215},"Item2":{"IsEmpty":false,"X":345.664856,"Y":373.04715}},
{"Item1":{"IsEmpty":false,"X":467.167236,"Y":425.13028},"Item2":{"IsEmpty":false,"X":408.1693,"Y":395.67215}},
{"Item1":{"IsEmpty":false,"X":522.0398,"Y":461.023956},"Item2":{"IsEmpty":false,"X":467.167236,"Y":425.13028}}]},
{"Color":"Purple","Path":[{"Item1":{"IsEmpty":false,"X":338.460724,"Y":368.026245},"Item2":{"IsEmpty":false,"X":335.717621,"Y":359.713959}}]},
{"Color":"Purple","Path":[{"Item1":{"IsEmpty":false,"X":338.870422,"Y":264.980774},"Item2":{"IsEmpty":false,"X":346.1596,"Y":259.8956}}]},
{"Color":"Purple","Path":[{"Item1":{"IsEmpty":false,"X":582.918,"Y":123.517548},"Item2":{"IsEmpty":false,"X":587.837036,"Y":122.446808}},
{"Item1":{"IsEmpty":false,"X":578.5587,"Y":126.318863},"Item2":{"IsEmpty":false,"X":582.918,"Y":123.517548}},
{"Item1":{"IsEmpty":false,"X":587.837036,"Y":122.446808},"Item2":{"IsEmpty":false,"X":595.4371,"Y":124.351707}},
{"Item1":{"IsEmpty":false,"X":595.4371,"Y":124.351707},"Item2":{"IsEmpty":false,"X":670.3067,"Y":168.303986}},
{"Item1":{"IsEmpty":false,"X":670.3067,"Y":168.303986},"Item2":{"IsEmpty":false,"X":676.080261,"Y":174.976364}},
{"Item1":{"IsEmpty":false,"X":676.080261,"Y":174.976364},"Item2":{"IsEmpty":false,"X":676.6656,"Y":183.869186}},
{"Item1":{"IsEmpty":false,"X":676.6656,"Y":183.869186},"Item2":{"IsEmpty":false,"X":663.597961,"Y":250.1111}},
{"Item1":{"IsEmpty":false,"X":670.7883,"Y":447.32135},"Item2":{"IsEmpty":false,"X":669.8241,"Y":455.952545}},
{"Item1":{"IsEmpty":false,"X":663.8524,"Y":462.422943},"Item2":{"IsEmpty":false,"X":588.65,"Y":504.8283}},
{"Item1":{"IsEmpty":false,"X":588.65,"Y":504.8283},"Item2":{"IsEmpty":false,"X":580.0528,"Y":506.5786}},
{"Item1":{"IsEmpty":false,"X":572.183838,"Y":502.9478},"Item2":{"IsEmpty":false,"X":522.0398,"Y":461.023956}},
{"Item1":{"IsEmpty":false,"X":345.664856,"Y":373.04715},"Item2":{"IsEmpty":false,"X":338.460724,"Y":368.026245}},
{"Item1":{"IsEmpty":false,"X":335.717621,"Y":359.713959},"Item2":{"IsEmpty":false,"X":336.047729,"Y":273.381378}},
{"Item1":{"IsEmpty":false,"X":336.047729,"Y":273.381378},"Item2":{"IsEmpty":false,"X":338.870422,"Y":264.980774}},
{"Item1":{"IsEmpty":false,"X":526.1518,"Y":169.835342},"Item2":{"IsEmpty":false,"X":578.5587,"Y":126.318863}},
{"Item1":{"IsEmpty":false,"X":469.585022,"Y":206.7812},"Item2":{"IsEmpty":false,"X":526.1518,"Y":169.835342}},
{"Item1":{"IsEmpty":false,"X":409.409851,"Y":236.892059},"Item2":{"IsEmpty":false,"X":469.585022,"Y":206.7812}},
{"Item1":{"IsEmpty":false,"X":346.1596,"Y":259.8956},"Item2":{"IsEmpty":false,"X":409.409851,"Y":236.892059}}]},
{"Color":"Purple","Path":[{"Item1":{"IsEmpty":false,"X":762.16626,"Y":149.617874},"Item2":{"IsEmpty":false,"X":765.2092,"Y":166.903931}},
{"Item1":{"IsEmpty":false,"X":752.9907,"Y":135.415756},"Item2":{"IsEmpty":false,"X":762.16626,"Y":149.617874}},
{"Item1":{"IsEmpty":false,"X":739.1052,"Y":125.794327},"Item2":{"IsEmpty":false,"X":752.9907,"Y":135.415756}}]},
{"Color":"Purple","Path":[{"Item1":{"IsEmpty":false,"X":729.4322,"Y":503.357727},"Item2":{"IsEmpty":false,"X":712.4581,"Y":506.765}},
{"Item1":{"IsEmpty":false,"X":743.52655,"Y":494.107666},"Item2":{"IsEmpty":false,"X":729.4322,"Y":503.357727}},
{"Item1":{"IsEmpty":false,"X":753.266541,"Y":480.425568},"Item2":{"IsEmpty":false,"X":743.52655,"Y":494.107666}}]},
{"Color":"Purple","Path":[{"Item1":{"IsEmpty":false,"X":729.6285,"Y":470.624237},"Item2":{"IsEmpty":false,"X":731.154053,"Y":463.739746}},
{"Item1":{"IsEmpty":false,"X":725.770569,"Y":476.145447},"Item2":{"IsEmpty":false,"X":729.6285,"Y":470.624237}},
{"Item1":{"IsEmpty":false,"X":720.0893,"Y":479.817566},"Item2":{"IsEmpty":false,"X":725.770569,"Y":476.145447}},
{"Item1":{"IsEmpty":false,"X":713.090332,"Y":481.154541},"Item2":{"IsEmpty":false,"X":720.0893,"Y":479.817566}},
{"Item1":{"IsEmpty":false,"X":731.154053,"Y":463.739746},"Item2":{"IsEmpty":false,"X":738.7705,"Y":166.901031}},
{"Item1":{"IsEmpty":false,"X":738.7705,"Y":166.901031},"Item2":{"IsEmpty":false,"X":737.581,"Y":159.784668}},
{"Item1":{"IsEmpty":false,"X":728.3512,"Y":150.26944},"Item2":{"IsEmpty":false,"X":721.2926,"Y":148.8876}},
{"Item1":{"IsEmpty":false,"X":733.944458,"Y":154.071274},"Item2":{"IsEmpty":false,"X":728.3512,"Y":150.26944}},
{"Item1":{"IsEmpty":false,"X":737.581,"Y":159.784668},"Item2":{"IsEmpty":false,"X":733.944458,"Y":154.071274}},
{"Item1":{"IsEmpty":false,"X":721.2926,"Y":148.8876},"Item2":{"IsEmpty":false,"X":676.147339,"Y":148.880386}},
{"Item1":{"IsEmpty":false,"X":676.147339,"Y":148.880386},"Item2":{"IsEmpty":false,"X":630.811,"Y":122.231407}},
{"Item1":{"IsEmpty":false,"X":630.811,"Y":122.231407},"Item2":{"IsEmpty":false,"X":721.950134,"Y":122.2528}},
{"Item1":{"IsEmpty":false,"X":721.950134,"Y":122.2528},"Item2":{"IsEmpty":false,"X":739.1052,"Y":125.794327}},
{"Item1":{"IsEmpty":false,"X":765.2092,"Y":166.903931},"Item2":{"IsEmpty":false,"X":757.1674,"Y":463.720917}},
{"Item1":{"IsEmpty":false,"X":757.1674,"Y":463.720917},"Item2":{"IsEmpty":false,"X":753.266541,"Y":480.425568}},
{"Item1":{"IsEmpty":false,"X":712.4581,"Y":506.765},"Item2":{"IsEmpty":false,"X":623.2144,"Y":506.840424}},
{"Item1":{"IsEmpty":false,"X":623.2144,"Y":506.840424},"Item2":{"IsEmpty":false,"X":668.757446,"Y":481.1888}},
{"Item1":{"IsEmpty":false,"X":668.757446,"Y":481.1888},"Item2":{"IsEmpty":false,"X":713.090332,"Y":481.154541}}]},
{"Color":"Purple","Path":[{"Item1":{"IsEmpty":false,"X":-83.40673,"Y":125.609421},"Item2":{"IsEmpty":false,"X":-66.15003,"Y":122.0678}},
{"Item1":{"IsEmpty":false,"X":-97.4226761,"Y":135.247543},"Item2":{"IsEmpty":false,"X":-83.40673,"Y":125.609421}},
{"Item1":{"IsEmpty":false,"X":-106.7388,"Y":149.480652},"Item2":{"IsEmpty":false,"X":-97.4226761,"Y":135.247543}}]},
{"Color":"Purple","Path":[{"Item1":{"IsEmpty":false,"X":-82.1057358,"Y":159.678619},"Item2":{"IsEmpty":false,"X":-83.3489,"Y":166.8111}},
{"Item1":{"IsEmpty":false,"X":-78.4137955,"Y":153.953156},"Item2":{"IsEmpty":false,"X":-82.1057358,"Y":159.678619}},
{"Item1":{"IsEmpty":false,"X":-72.76941,"Y":150.1444},"Item2":{"IsEmpty":false,"X":-78.4137955,"Y":153.953156}}]},
{"Color":"Purple","Path":[{"Item1":{"IsEmpty":false,"X":-66.70246,"Y":480.422729},"Item2":{"IsEmpty":false,"X":-59.6818657,"Y":481.7518}},
{"Item1":{"IsEmpty":false,"X":-72.38421,"Y":476.751129},"Item2":{"IsEmpty":false,"X":-66.70246,"Y":480.422729}},
{"Item1":{"IsEmpty":false,"X":-76.2221451,"Y":471.223267},"Item2":{"IsEmpty":false,"X":-72.38421,"Y":476.751129}}]},
{"Color":"Purple","Path":[{"Item1":{"IsEmpty":false,"X":548.180969,"Y":506.9038},"Item2":{"IsEmpty":false,"X":-59.2203331,"Y":507.416931}},
{"Item1":{"IsEmpty":false,"X":-59.2203331,"Y":507.416931},"Item2":{"IsEmpty":false,"X":-76.24668,"Y":504.0307}},
{"Item1":{"IsEmpty":false,"X":-100.036964,"Y":481.0834},"Item2":{"IsEmpty":false,"X":-103.843513,"Y":464.34433}},
{"Item1":{"IsEmpty":false,"X":-90.3434,"Y":494.782532},"Item2":{"IsEmpty":false,"X":-100.036964,"Y":481.0834}},
{"Item1":{"IsEmpty":false,"X":-76.24668,"Y":504.0307},"Item2":{"IsEmpty":false,"X":-90.3434,"Y":494.782532}},
{"Item1":{"IsEmpty":false,"X":-103.843513,"Y":464.34433},"Item2":{"IsEmpty":false,"X":-109.913765,"Y":166.8082}},
{"Item1":{"IsEmpty":false,"X":-109.913765,"Y":166.8082},"Item2":{"IsEmpty":false,"X":-106.7388,"Y":149.480652}},
{"Item1":{"IsEmpty":false,"X":-66.15003,"Y":122.0678},"Item2":{"IsEmpty":false,"X":554.179749,"Y":122.213417}},
{"Item1":{"IsEmpty":false,"X":554.179749,"Y":122.213417},"Item2":{"IsEmpty":false,"X":521.7652,"Y":148.8557}},
{"Item1":{"IsEmpty":false,"X":521.7652,"Y":148.8557},"Item2":{"IsEmpty":false,"X":-65.66999,"Y":148.761719}},
{"Item1":{"IsEmpty":false,"X":-65.66999,"Y":148.761719},"Item2":{"IsEmpty":false,"X":-72.76941,"Y":150.1444}},
{"Item1":{"IsEmpty":false,"X":-83.3489,"Y":166.8111},"Item2":{"IsEmpty":false,"X":-77.70803,"Y":464.3254}},
{"Item1":{"IsEmpty":false,"X":-77.70803,"Y":464.3254},"Item2":{"IsEmpty":false,"X":-76.2221451,"Y":471.223267}},
{"Item1":{"IsEmpty":false,"X":-59.6818657,"Y":481.7518},"Item2":{"IsEmpty":false,"X":517.1584,"Y":481.305969}},
{"Item1":{"IsEmpty":false,"X":517.1584,"Y":481.305969},"Item2":{"IsEmpty":false,"X":548.180969,"Y":506.9038}}]},
{"Color":"Purple","Path":[{"Item1":{"IsEmpty":false,"X":262.919983,"Y":177.175186},"Item2":{"IsEmpty":false,"X":268.7695,"Y":181.30397}}]},
{"Color":"Purple","Path":[{"Item1":{"IsEmpty":false,"X":272.7552,"Y":187.251282},"Item2":{"IsEmpty":false,"X":274.080872,"Y":194.43483}}]},
{"Color":"Purple","Path":[{"Item1":{"IsEmpty":false,"X":272.617767,"Y":444.538025},"Item2":{"IsEmpty":false,"X":268.5548,"Y":450.4039}}]},
{"Color":"Purple","Path":[{"Item1":{"IsEmpty":false,"X":262.703949,"Y":454.286346},"Item2":{"IsEmpty":false,"X":255.6327,"Y":455.583771}}]},
{"Color":"Purple","Path":[{"Item1":{"IsEmpty":false,"X":248.6468,"Y":454.296143},"Item2":{"IsEmpty":false,"X":242.70488,"Y":450.421631}}]},
{"Color":"Purple","Path":[{"Item1":{"IsEmpty":false,"X":238.765839,"Y":444.5607},"Item2":{"IsEmpty":false,"X":237.444443,"Y":437.6575}}]},
{"Color":"Purple","Path":[{"Item1":{"IsEmpty":false,"X":208.058838,"Y":225.017578},"Item2":{"IsEmpty":false,"X":202.075638,"Y":221.172943}},
{"Item1":{"IsEmpty":false,"X":215.358536,"Y":226.29805},"Item2":{"IsEmpty":false,"X":208.058838,"Y":225.017578}},
{"Item1":{"IsEmpty":false,"X":202.075638,"Y":221.172943},"Item2":{"IsEmpty":false,"X":198.205719,"Y":215.203186}},
{"Item1":{"IsEmpty":false,"X":198.205719,"Y":215.203186},"Item2":{"IsEmpty":false,"X":196.895584,"Y":207.900223}},
{"Item1":{"IsEmpty":false,"X":196.895584,"Y":207.900223},"Item2":{"IsEmpty":false,"X":199.6916,"Y":197.8018}},
{"Item1":{"IsEmpty":false,"X":199.6916,"Y":197.8018},"Item2":{"IsEmpty":false,"X":208.704117,"Y":190.530228}},
{"Item1":{"IsEmpty":false,"X":208.704117,"Y":190.530228},"Item2":{"IsEmpty":false,"X":249.268051,"Y":177.040619}},
{"Item1":{"IsEmpty":false,"X":249.268051,"Y":177.040619},"Item2":{"IsEmpty":false,"X":255.650772,"Y":175.797256}},
{"Item1":{"IsEmpty":false,"X":255.650772,"Y":175.797256},"Item2":{"IsEmpty":false,"X":262.919983,"Y":177.175186}},
{"Item1":{"IsEmpty":false,"X":268.7695,"Y":181.30397},"Item2":{"IsEmpty":false,"X":272.7552,"Y":187.251282}},
{"Item1":{"IsEmpty":false,"X":274.080872,"Y":194.43483},"Item2":{"IsEmpty":false,"X":273.97406,"Y":437.633759}},
{"Item1":{"IsEmpty":false,"X":273.97406,"Y":437.633759},"Item2":{"IsEmpty":false,"X":272.617767,"Y":444.538025}},
{"Item1":{"IsEmpty":false,"X":268.5548,"Y":450.4039},"Item2":{"IsEmpty":false,"X":262.703949,"Y":454.286346}},
{"Item1":{"IsEmpty":false,"X":255.6327,"Y":455.583771},"Item2":{"IsEmpty":false,"X":248.6468,"Y":454.296143}},
{"Item1":{"IsEmpty":false,"X":242.70488,"Y":450.421631},"Item2":{"IsEmpty":false,"X":238.765839,"Y":444.5607}},
{"Item1":{"IsEmpty":false,"X":237.444443,"Y":437.6575},"Item2":{"IsEmpty":false,"X":237.102264,"Y":220.109833}},
{"Item1":{"IsEmpty":false,"X":237.102264,"Y":220.109833},"Item2":{"IsEmpty":false,"X":225.96524,"Y":224.176361}},
{"Item1":{"IsEmpty":false,"X":225.96524,"Y":224.176361},"Item2":{"IsEmpty":false,"X":215.358536,"Y":226.29805}}]}]